kobushi/__init__.py
kobushi/__main__.py
kobushi/_version.py
kobushi/dialog_multifields.py
kobushi/font_window.py
kobushi/gui_interface.py
kobushi/loadheader.py
kobushi/loadmapgrammer.py
kobushi/map-grammer.lark
kobushi/mapinterpreter.py
kobushi/mapobj.py
kobushi/mapplot.py
kobushi/othertrack_window.py
kobushi/trackcoordinate.py
kobushi/trackgenerator.py
kobushi_trackviewer-1.2.2.dist-info/LICENSE
kobushi_trackviewer-1.2.2.dist-info/METADATA
kobushi_trackviewer-1.2.2.dist-info/WHEEL
kobushi_trackviewer-1.2.2.dist-info/top_level.txt
kobushi_trackviewer-1.2.2.dist-info/RECORD
