Metadata-Version: 2.1
Name: kobushi-trackviewer
Version: 1.2.2
Summary: Trackviewer for BVE trainsim 5/6
Home-page: https://github.com/konawasabi/kobushi-trackviewer/
Author: Konawasabi
Author-email: webmaster@konawasabi.riceball.jp
License: Apache License 2.0
Keywords: BVE trainsim
License-File: LICENSE
Requires-Dist: scipy>=1.13.0
Requires-Dist: matplotlib>=3.8.4
Requires-Dist: ttkwidgets>=0.13.0
Requires-Dist: lark>=1.1.9
